json_python_flatten/__init__.py
json_python_flatten/flatten.py
json_python_flatten/unflatten.py
json_python_flatten-0.1.3.dist-info/LICENSE
json_python_flatten-0.1.3.dist-info/METADATA
json_python_flatten-0.1.3.dist-info/WHEEL
json_python_flatten-0.1.3.dist-info/top_level.txt
json_python_flatten-0.1.3.dist-info/RECORD
