Metadata-Version: 2.1
Name: json-python-flatten
Version: 0.1.3
Summary: Flatten JSON objects
Home-page: https://github.com/drg0072/json_flatten
Author: Dheeraj Gupta
Author-email: drg0072@gmail.com
License: MIT
Keywords: json,flatten
Platform: UNKNOWN
